Workbook

Sheet READ ME
A1: ACE — RENT & DAMAGES WORKSHEET (Inocalla Estate)
A3: Purpose: quantify the money claim against Vicente Inocalla III ('Ace') & group for occupying and renting
A4: the estate's Manila apartment units and Paracale land, plus related damages. Companion to ACE_DAMAGES_FRAMEWORK.md.
A6: HOW TO USE:
A7: 1. Fill only the YELLOW cells (blue text = you type it). Black cells are formulas — do not overwrite.
A8: 2. Set the Valuation Date on the 'Manila Units' tab (default 2026-07-04). Leave a unit's 'End' blank if still occupied.
A9: 3. Totals roll up automatically to the SUMMARY tab.
A11: COLOR KEY: yellow cell / blue text = input you provide | black = formula | green = links from another tab
A13: LEGAL CAUTIONS (read before relying on totals):
A14: - EJECTMENT (MeTC) recovers only the Manila fair-rental value + attorney's fees. The rest (fruits collected,
A15: exemplary, moral, Paracale land, litigation cost) belongs in a SEPARATE damages action (RTC).
A16: - DO NOT claim the same Manila rents in both cases (anti-splitting / forum-shopping). The SUMMARY marks which
... A22: Prepared 2026-07-04. Fill with the family; confirm figures with counsel.

Sheet Manila Units
A1: MANILA BUILDING — 2531 G. Del Pilar St., Sta. Ana, Manila (TCT 44055) — lost rents / fair rental value
A3: Valuation Date (used when a unit's End is blank): | D3: 46207
A5: Unit # | B5: Description / Floor | C5: Occupant (Ace group?) | D5: Occupation Start | E5: Period End (blank = still occupied) | F5: Months (auto) | G5: Fair Monthly Rent ₱ | H5: Fair Rental Value ₱ (auto) | I5: Rents Ace Actually Collected ₱ (if known) | J5: Notes
A6: 1 | F6: =IF(D6="","",ROUND((IF(E6="",$D$3,E6)-D6)/30.4375,1)) | H6: =IF(OR(F6="",G6=""),0,F6*G6) -> 0
A7: 2 | F7: =IF(D7="","",ROUND((IF(E7="",$D$3,E7)-D7)/30.4375,1)) | H7: =IF(OR(F7="",G7=""),0,F7*G7) -> 0
A8: 3 | F8: =IF(D8="","",ROUND((IF(E8="",$D$3,E8)-D8)/30.4375,1)) | H8: =IF(OR(F8="",G8=""),0,F8*G8) -> 0
A9: 4 | F9: =IF(D9="","",ROUND((IF(E9="",$D$3,E9)-D9)/30.4375,1)) | H9: =IF(OR(F9="",G9=""),0,F9*G9) -> 0
A10: 5 | F10: =IF(D10="","",ROUND((IF(E10="",$D$3,E10)-D10)/30.4375,1)) | H10: =IF(OR(F10="",G10=""),0,F10*G10) -> 0
A11: 6 | F11: =IF(D11="","",ROUND((IF(E11="",$D$3,E11)-D11)/30.4375,1)) | H11: =IF(OR(F11="",G11=""),0,F11*G11) -> 0
A12: 7 | F12: =IF(D12="","",ROUND((IF(E12="",$D$3,E12)-D12)/30.4375,1)) | H12: =IF(OR(F12="",G12=""),0,F12*G12) -> 0
A13: 8 | F13: =IF(D13="","",ROUND((IF(E13="",$D$3,E13)-D13)/30.4375,1)) | H13: =IF(OR(F13="",G13=""),0,F13*G13) -> 0
A14: 9 | F14: =IF(D14="","",ROUND((IF(E14="",$D$3,E14)-D14)/30.4375,1)) | H14: =IF(OR(F14="",G14=""),0,F14*G14) -> 0
A15: 10 | F15: =IF(D15="","",ROUND((IF(E15="",$D$3,E15)-D15)/30.4375,1)) | H15: =IF(OR(F15="",G15=""),0,F15*G15) -> 0
A16: TOTAL | H16: =SUM(H6:H15) -> 0 | I16: =SUM(I6:I15) -> 0
A18: Per Complaint vs Ace (docs 644/526): the group occupied the units of Allan, Jesus, Casper, Melvin, Francisco (NOT Cipriana's or Senen's) and rented them.

Sheet Paracale Land
A1: PARACALE ESTATE LAND — reasonable value of use during Ace occupation (~25 ha, Front 1A)
A3: Valuation Date: | C3: ='Manila Units'!D3 -> 46207
A5: Parcel / Title | B5: Area (ha) | C5: Occupation Start | D5: Period End (blank = now) | E5: Months (auto) | F5: Fair Use Value ₱ / ha / month | G5: Total ₱ (auto) | H5: Notes
E6: =IF(C6="","",ROUND((IF(D6="",$C$3,D6)-C6)/30.4375,1)) | G6: =IF(OR(B6="",E6="",F6=""),0,B6*E6*F6) -> 0
E7: =IF(C7="","",ROUND((IF(D7="",$C$3,D7)-C7)/30.4375,1)) | G7: =IF(OR(B7="",E7="",F7=""),0,B7*E7*F7) -> 0
E8: =IF(C8="","",ROUND((IF(D8="",$C$3,D8)-C8)/30.4375,1)) | G8: =IF(OR(B8="",E8="",F8=""),0,B8*E8*F8) -> 0
E9: =IF(C9="","",ROUND((IF(D9="",$C$3,D9)-C9)/30.4375,1)) | G9: =IF(OR(B9="",E9="",F9=""),0,B9*E9*F9) -> 0
A10: TOTAL | G10: =SUM(G6:G9) -> 0

Sheet Other Damages
A1: OTHER DAMAGES (the separate RTC damages action)
A3: Head of Damages | B3: Legal Basis | C3: Claimed by | D3: Amount ₱ | E3: Notes / how to prove
A4: Rents Ace actually collected (fruits, bad faith) | B4: Civil Code Arts. 549, 552 | C4: Estate | D4: ='Manila Units'!I15 -> 0 | E4: Auto-linked from Manila Units total; a possessor in bad faith returns fruits received
A5: Attorney's fees & litigation expenses | B5: Art. 2208 (1)(2)(5) | C5: Estate | E5: Estate's counsel billings across CA SP 161072 / SC G.R. 256997 / the Dec-2025 MR
A6: Exemplary damages | B6: Arts. 2229-2234 | C6: Estate / heirs | E6: Predicate = judicially-found bad-faith buyer + conspiracy; court discretion
A7: Moral damages | B7: Arts. 2217, 2219-2220 | C7: Individual heirs (personal) | E7: Affidavits of harassed heirs (Marilou, Jesus, etc.) — anxiety from threats/bullying
A8: Temperate / nominal (fallback) | B8: Arts. 2224 / 2221 | C8: Estate | E8: Use only if exact amounts unprovable
A9: TOTAL (other damages) | D9: =SUM(D4:D8) -> 0

Sheet SUMMARY
A1: SUMMARY — total money claim vs Ace
A3: Head | B3: Amount ₱ | C3: Forum (where claimed)
A4: Manila fair rental value (lost use of the 10 units) | B4: ='Manila Units'!H15 -> 0 | C4: EJECTMENT (MeTC) — reasonable compensation
A5: Rents Ace actually collected (fruits) | B5: ='Other Damages'!D4 -> 0 | C5: Damages suit (RTC)
A6: Paracale land — reasonable value of use | B6: ='Paracale Land'!G10 -> 0 | C6: Damages suit (RTC)
A7: Attorney's fees & litigation expenses | B7: ='Other Damages'!D5 -> 0 | C7: Damages suit (RTC)
A8: Exemplary damages | B8: ='Other Damages'!D6 -> 0 | C8: Damages suit (RTC)
A9: Moral damages (heirs, personal) | B9: ='Other Damages'!D7 -> 0 | C9: Damages suit (RTC)
A10: GRAND TOTAL (all heads) | B10: =SUM(B4:B9) -> 0
A12: NOTE: the Manila fair-rental row is claimed in the EJECTMENT; do not also claim it in the damages suit. Fruits collected are the distinct bad-faith measure for the RTC action.
